[
  {
    "id": "naikaku-shijiritsu-teika-kikikan",
    "title": "内閣支持率減 与党に危機感 皇室典範改正・国会運営が影響",
    "subtitle": "高市内閣の支持率が下落。典範改正と強引な国会運営が要因か。食料品減税の判断迫られる。",
    "level": "中級",
    "length": 3,
    "date": "2026-07-24",
    "paragraphs": [
      {
        "id": "p1",
        "ja": "報道各社の世論調査で高市内閣の支持率が下落している。皇室典範の改正や与党の国会運営が影響したとの見方が広がる。時事通信の7月の調査では支持率は49.0％で政権発足後の最低を記録。毎日新聞の調査でも支持率は10ポイント減の41％に落ち込んだ。",
        "en": "Approval ratings for the Takaichi Cabinet are declining across media polls. A widespread view attributes this to the revision of the Imperial House Law and the ruling party's Diet management. In Jiji Press's July survey, the approval rate dropped to 49.0%, the lowest since the administration took office. Mainichi Shimbun's survey also showed a 10-point drop to 41%.",
        "literal": "各媒体报道的舆论调查显示高市内阁的支持率正在下降。广泛的看法是皇室典范的修改和执政党的国会运营产生了影响。时事通信的7月调查中支持率为49.0%，是政权成立后的最低纪录。每日新闻的调查中支持率也下降了10个百分点至41%。",
        "grammar": "「〜で下落する」— 在…方面下降。例：支持率が下落（支持率下降）。\n「〜との見方」— …的看法。例：影響したとの見方（认为产生了影响的看法）。\n「〜に落ち込む」— 跌至…。例：41％に落ち込んだ（跌至41%）。",
        "vocab": [
          [
            "世論調査",
            "よろんちょうさ",
            "舆论调查"
          ],
          [
            "支持率",
            "しじりつ",
            "支持率"
          ],
          [
            "下落する",
            "げらくする",
            "下降、下跌"
          ],
          [
            "政権",
            "せいけん",
            "政权"
          ],
          [
            "発足",
            "ほっそく",
            "成立、启动"
          ],
          [
            "最低",
            "さいてい",
            "最低"
          ]
        ],
        "words": [
          {
            "s": "報道",
            "r": "ほうどう",
            "p": "noun"
          },
          {
            "s": "各社",
            "r": "かくしゃ",
            "p": "noun"
          },
          {
            "s": "の",
            "r": "",
            "p": "particle"
          },
          {
            "s": "世論",
            "r": "よろん",
            "p": "noun"
          },
          {
            "s": "調査",
            "r": "ちょうさ",
            "p": "noun"
          },
          {
            "s": "で",
            "r": "",
            "p": "particle"
          },
          {
            "s": "高市",
            "r": "たかいち",
            "p": "noun"
          },
          {
            "s": "内閣",
            "r": "ないかく",
            "p": "noun"
          },
          {
            "s": "の",
            "r": "",
            "p": "particle"
          },
          {
            "s": "支持率",
            "r": "しじりつ",
            "p": "noun"
          },
          {
            "s": "が",
            "r": "",
            "p": "particle"
          },
          {
            "s": "下落",
            "r": "げらく",
            "p": "noun"
          },
          {
            "s": "する",
            "r": "",
            "p": "verb"
          },
          {
            "s": "て",
            "r": "",
            "p": "particle"
          },
          {
            "s": "いる",
            "r": "",
            "p": "verb"
          },
          {
            "s": "。",
            "r": "",
            "p": ""
          },
          {
            "s": "皇室",
            "r": "こうしつ",
            "p": "noun"
          },
          {
            "s": "典範",
            "r": "てんぱん",
            "p": "noun"
          },
          {
            "s": "の",
            "r": "",
            "p": "particle"
          },
          {
            "s": "改正",
            "r": "かいせい",
            "p": "noun"
          },
          {
            "s": "や",
            "r": "",
            "p": "particle"
          },
          {
            "s": "与党",
            "r": "よとう",
            "p": "noun"
          },
          {
            "s": "の",
            "r": "",
            "p": "particle"
          },
          {
            "s": "国会",
            "r": "こっかい",
            "p": "noun"
          },
          {
            "s": "運営",
            "r": "うんえい",
            "p": "noun"
          },
          {
            "s": "が",
            "r": "",
            "p": "particle"
          },
          {
            "s": "影響",
            "r": "えいきょう",
            "p": "noun"
          },
          {
            "s": "する",
            "r": "",
            "p": "verb"
          },
          {
            "s": "た",
            "r": "",
            "p": "grammar"
          },
          {
            "s": "と",
            "r": "",
            "p": "particle"
          },
          {
            "s": "の",
            "r": "",
            "p": "particle"
          },
          {
            "s": "見方",
            "r": "みかた",
            "p": "noun"
          },
          {
            "s": "が",
            "r": "",
            "p": "particle"
          },
          {
            "s": "広がる",
            "r": "ひろがる",
            "p": "verb"
          },
          {
            "s": "。",
            "r": "",
            "p": ""
          },
          {
            "s": "時事",
            "r": "じじ",
            "p": "noun"
          },
          {
            "s": "通信",
            "r": "つうしん",
            "p": "noun"
          },
          {
            "s": "の",
            "r": "",
            "p": "particle"
          },
          {
            "s": "7",
            "r": "なな",
            "p": "noun"
          },
          {
            "s": "月",
            "r": "がつ",
            "p": "noun"
          },
          {
            "s": "の",
            "r": "",
            "p": "particle"
          },
          {
            "s": "調査",
            "r": "ちょうさ",
            "p": "noun"
          },
          {
            "s": "で",
            "r": "",
            "p": "particle"
          },
          {
            "s": "は",
            "r": "",
            "p": "particle"
          },
          {
            "s": "支持率",
            "r": "しじりつ",
            "p": "noun"
          },
          {
            "s": "は",
            "r": "",
            "p": "particle"
          },
          {
            "s": "49.0",
            "r": "よんきゅう．れい",
            "p": "noun"
          },
          {
            "s": "%",
            "r": "ぱーせんと",
            "p": "noun"
          },
          {
            "s": "で",
            "r": "",
            "p": "particle"
          },
          {
            "s": "政権",
            "r": "せいけん",
            "p": "noun"
          },
          {
            "s": "発足",
            "r": "ほっそく",
            "p": "noun"
          },
          {
            "s": "後",
            "r": "ご",
            "p": "connector"
          },
          {
            "s": "の",
            "r": "",
            "p": "particle"
          },
          {
            "s": "最低",
            "r": "さいてい",
            "p": "noun"
          },
          {
            "s": "を",
            "r": "",
            "p": "particle"
          },
          {
            "s": "記録",
            "r": "きろく",
            "p": "noun"
          },
          {
            "s": "。",
            "r": "",
            "p": ""
          },
          {
            "s": "毎日",
            "r": "まいにち",
            "p": "noun"
          },
          {
            "s": "新聞",
            "r": "しんぶん",
            "p": "noun"
          },
          {
            "s": "の",
            "r": "",
            "p": "particle"
          },
          {
            "s": "調査",
            "r": "ちょうさ",
            "p": "noun"
          },
          {
            "s": "で",
            "r": "",
            "p": "particle"
          },
          {
            "s": "も",
            "r": "",
            "p": "particle"
          },
          {
            "s": "支持率",
            "r": "しじりつ",
            "p": "noun"
          },
          {
            "s": "は",
            "r": "",
            "p": "particle"
          },
          {
            "s": "10",
            "r": "いちれい",
            "p": "noun"
          },
          {
            "s": "ポイント",
            "r": "ぽいんと",
            "p": "noun"
          },
          {
            "s": "減",
            "r": "げん",
            "p": "noun"
          },
          {
            "s": "の",
            "r": "",
            "p": "particle"
          },
          {
            "s": "41",
            "r": "よんいち",
            "p": "noun"
          },
          {
            "s": "%",
            "r": "ぱーせんと",
            "p": "noun"
          },
          {
            "s": "に",
            "r": "",
            "p": "particle"
          },
          {
            "s": "落ち込む",
            "r": "おちこん",
            "p": "verb"
          },
          {
            "s": "だ",
            "r": "",
            "p": "grammar"
          },
          {
            "s": "。",
            "r": "",
            "p": ""
          }
        ],
        "audio": "assets/audio/naikaku-shijiritsu-teika-kikikan/p1.mp3"
      },
      {
        "id": "p2",
        "ja": "与党からは深刻な受け止めが出ている。閣僚の一人は支持下落の理由について「皇室典範と強引な国会運営だ」と指摘した。典範改正を巡っては旧宮家の男系男子を養子として迎えることに国民の理解が得られていないとの声が根強い。首相の国会対応にも批判が集まっている。",
        "en": "Serious concerns have emerged from within the ruling party. One cabinet minister pointed to 'the Imperial House Law and forceful Diet management' as reasons for the declining support. Regarding the law revision, there is persistent criticism that public understanding has not been gained for the plan to bring male descendants of former imperial families into the imperial household as adoptees. The Prime Minister's Diet handling has also drawn criticism.",
        "literal": "执政党内部出现了严重的反应。一位阁僚指出支持率下降的原因「是皇室典范和强行国会运营」。围绕典范修改，关于将旧宫家男系男子作为养子迎入皇室一事根深蒂固地存在着国民理解不足的声音。首相的国会应对也受到批评。",
        "grammar": "「〜について」— 关于…。例：理由について（关于理由）。\n「〜を巡って」— 围绕…。例：典範改正を巡って（围绕典范修改）。\n「〜との声」— …的声音。例：得られていないとの声（没有得到理解的声音）。",
        "vocab": [
          [
            "深刻",
            "しんこく",
            "深刻"
          ],
          [
            "受け止め",
            "うけとめ",
            "接受、反应"
          ],
          [
            "閣僚",
            "かくりょう",
            "阁僚、部长"
          ],
          [
            "強引",
            "ごういん",
            "强行、强硬"
          ],
          [
            "旧宮家",
            "きゅうみやけ",
            "旧宫家（皇室分支）"
          ],
          [
            "養子",
            "ようし",
            "养子"
          ]
        ],
        "words": [
          {
            "s": "与党",
            "r": "よとう",
            "p": "noun"
          },
          {
            "s": "から",
            "r": "",
            "p": "particle"
          },
          {
            "s": "は",
            "r": "",
            "p": "particle"
          },
          {
            "s": "深刻",
            "r": "しんこく",
            "p": ""
          },
          {
            "s": "だ",
            "r": "",
            "p": "grammar"
          },
          {
            "s": "受け止める",
            "r": "うけとめ",
            "p": "verb"
          },
          {
            "s": "が",
            "r": "",
            "p": "particle"
          },
          {
            "s": "出る",
            "r": "で",
            "p": "verb"
          },
          {
            "s": "て",
            "r": "",
            "p": "particle"
          },
          {
            "s": "いる",
            "r": "",
            "p": "verb"
          },
          {
            "s": "。",
            "r": "",
            "p": ""
          },
          {
            "s": "閣僚",
            "r": "かくりょう",
            "p": "noun"
          },
          {
            "s": "の",
            "r": "",
            "p": "particle"
          },
          {
            "s": "一人",
            "r": "ひとり",
            "p": "noun"
          },
          {
            "s": "は",
            "r": "",
            "p": "particle"
          },
          {
            "s": "支持",
            "r": "しじ",
            "p": "noun"
          },
          {
            "s": "下落",
            "r": "げらく",
            "p": "noun"
          },
          {
            "s": "の",
            "r": "",
            "p": "particle"
          },
          {
            "s": "理由",
            "r": "りゆう",
            "p": "noun"
          },
          {
            "s": "に",
            "r": "",
            "p": "particle"
          },
          {
            "s": "つく",
            "r": "",
            "p": "verb"
          },
          {
            "s": "て",
            "r": "",
            "p": "particle"
          },
          {
            "s": "「",
            "r": "",
            "p": ""
          },
          {
            "s": "皇室",
            "r": "こうしつ",
            "p": "noun"
          },
          {
            "s": "典範",
            "r": "てんぱん",
            "p": "noun"
          },
          {
            "s": "と",
            "r": "",
            "p": "particle"
          },
          {
            "s": "強引",
            "r": "ごういん",
            "p": ""
          },
          {
            "s": "だ",
            "r": "",
            "p": "grammar"
          },
          {
            "s": "国会",
            "r": "こっかい",
            "p": "noun"
          },
          {
            "s": "運営",
            "r": "うんえい",
            "p": "noun"
          },
          {
            "s": "だ",
            "r": "",
            "p": "grammar"
          },
          {
            "s": "」",
            "r": "",
            "p": ""
          },
          {
            "s": "と",
            "r": "",
            "p": "particle"
          },
          {
            "s": "指摘",
            "r": "してき",
            "p": "noun"
          },
          {
            "s": "する",
            "r": "",
            "p": "verb"
          },
          {
            "s": "た",
            "r": "",
            "p": "grammar"
          },
          {
            "s": "。",
            "r": "",
            "p": ""
          },
          {
            "s": "典範",
            "r": "てんぱん",
            "p": "noun"
          },
          {
            "s": "改正",
            "r": "かいせい",
            "p": "noun"
          },
          {
            "s": "を",
            "r": "",
            "p": "particle"
          },
          {
            "s": "巡る",
            "r": "めぐっ",
            "p": "verb"
          },
          {
            "s": "て",
            "r": "",
            "p": "particle"
          },
          {
            "s": "は",
            "r": "",
            "p": "particle"
          },
          {
            "s": "旧宮",
            "r": "きゅうきゅう",
            "p": "noun"
          },
          {
            "s": "家",
            "r": "や",
            "p": "connector"
          },
          {
            "s": "の",
            "r": "",
            "p": "particle"
          },
          {
            "s": "男系",
            "r": "だんけい",
            "p": "noun"
          },
          {
            "s": "男子",
            "r": "だんし",
            "p": "noun"
          },
          {
            "s": "を",
            "r": "",
            "p": "particle"
          },
          {
            "s": "養子",
            "r": "ようし",
            "p": "noun"
          },
          {
            "s": "と",
            "r": "",
            "p": "particle"
          },
          {
            "s": "する",
            "r": "",
            "p": "verb"
          },
          {
            "s": "て",
            "r": "",
            "p": "particle"
          },
          {
            "s": "迎える",
            "r": "むかえる",
            "p": "verb"
          },
          {
            "s": "こと",
            "r": "",
            "p": "noun"
          },
          {
            "s": "に",
            "r": "",
            "p": "particle"
          },
          {
            "s": "国民",
            "r": "こくみん",
            "p": "noun"
          },
          {
            "s": "の",
            "r": "",
            "p": "particle"
          },
          {
            "s": "理解",
            "r": "りかい",
            "p": "noun"
          },
          {
            "s": "が",
            "r": "",
            "p": "particle"
          },
          {
            "s": "得る",
            "r": "え",
            "p": "verb"
          },
          {
            "s": "られる",
            "r": "",
            "p": "grammar"
          },
          {
            "s": "て",
            "r": "",
            "p": "particle"
          },
          {
            "s": "いる",
            "r": "",
            "p": "verb"
          },
          {
            "s": "ない",
            "r": "",
            "p": "grammar"
          },
          {
            "s": "と",
            "r": "",
            "p": "particle"
          },
          {
            "s": "の",
            "r": "",
            "p": "particle"
          },
          {
            "s": "声",
            "r": "こえ",
            "p": "noun"
          },
          {
            "s": "が",
            "r": "",
            "p": "particle"
          },
          {
            "s": "根強い",
            "r": "ねづよい",
            "p": "adj"
          },
          {
            "s": "。",
            "r": "",
            "p": ""
          },
          {
            "s": "首相",
            "r": "しゅしょう",
            "p": "noun"
          },
          {
            "s": "の",
            "r": "",
            "p": "particle"
          },
          {
            "s": "国会",
            "r": "こっかい",
            "p": "noun"
          },
          {
            "s": "対応",
            "r": "たいおう",
            "p": "noun"
          },
          {
            "s": "に",
            "r": "",
            "p": "particle"
          },
          {
            "s": "も",
            "r": "",
            "p": "particle"
          },
          {
            "s": "批判",
            "r": "ひはん",
            "p": "noun"
          },
          {
            "s": "が",
            "r": "",
            "p": "particle"
          },
          {
            "s": "集まる",
            "r": "あつまっ",
            "p": "verb"
          },
          {
            "s": "て",
            "r": "",
            "p": "particle"
          },
          {
            "s": "いる",
            "r": "",
            "p": "verb"
          },
          {
            "s": "。",
            "r": "",
            "p": ""
          }
        ],
        "audio": "assets/audio/naikaku-shijiritsu-teika-kikikan/p2.mp3"
      },
      {
        "id": "p3",
        "ja": "物価高対策の遅れも支持離れを招いたとの見方がある。首相は近く食料品の消費税減税の判断を迫られる。与党は衆院選公約で2年間の税率ゼロを掲げていたが、自民関係者は「消費税を1％に下げる中途半端な対応では支持率がさらに落ち込む」と懸念している。",
        "en": "There is also a view that delays in addressing rising prices have led to declining support. The Prime Minister will soon face a decision on reducing the consumption tax on food items. The ruling party had promised a zero tax rate for two years in their Lower House election manifesto, but LDP insiders are concerned that 'a half-baked measure reducing the consumption tax to just 1% would cause approval ratings to fall even further.'",
        "literal": "物价高涨对策的滞后也被认为导致了支持率下降。首相近期被迫就食品消费税减税做出判断。执政党在众议院选举公约中提出了两年税率为零的承诺，但自民党相关人士担心「将消费税降至1%的半吊子应对会导致支持率进一步下降」。",
        "grammar": "「〜を招く」— 招致…。例：支持離れを招いた（招致了支持率下降）。\n「〜を迫られる」— 被迫…。例：判断を迫られる（被迫做出判断）。\n「〜では」— 如果是…的话（负面条件）。例：中途半端な対応では（如果是半吊子的应对的话）。",
        "vocab": [
          [
            "物価高",
            "ぶっかだか",
            "物价高涨"
          ],
          [
            "対策",
            "たいさく",
            "对策"
          ],
          [
            "消費税",
            "しょうひぜい",
            "消费税"
          ],
          [
            "減税",
            "げんぜい",
            "减税"
          ],
          [
            "公約",
            "こうやく",
            "公约、承诺"
          ],
          [
            "中途半端",
            "ちゅうとはんぱ",
            "半吊子、不彻底"
          ]
        ],
        "words": [
          {
            "s": "物価高",
            "r": "ぶっかだか",
            "p": "noun"
          },
          {
            "s": "対策",
            "r": "たいさく",
            "p": "noun"
          },
          {
            "s": "の",
            "r": "",
            "p": "particle"
          },
          {
            "s": "遅れ",
            "r": "おくれ",
            "p": "noun"
          },
          {
            "s": "も",
            "r": "",
            "p": "particle"
          },
          {
            "s": "支持",
            "r": "しじ",
            "p": "noun"
          },
          {
            "s": "離れ",
            "r": "はなれ",
            "p": "noun"
          },
          {
            "s": "を",
            "r": "",
            "p": "particle"
          },
          {
            "s": "招く",
            "r": "まねい",
            "p": "verb"
          },
          {
            "s": "た",
            "r": "",
            "p": "grammar"
          },
          {
            "s": "と",
            "r": "",
            "p": "particle"
          },
          {
            "s": "の",
            "r": "",
            "p": "particle"
          },
          {
            "s": "見方",
            "r": "みかた",
            "p": "noun"
          },
          {
            "s": "が",
            "r": "",
            "p": "particle"
          },
          {
            "s": "ある",
            "r": "",
            "p": "verb"
          },
          {
            "s": "。",
            "r": "",
            "p": ""
          },
          {
            "s": "首相",
            "r": "しゅしょう",
            "p": "noun"
          },
          {
            "s": "は",
            "r": "",
            "p": "particle"
          },
          {
            "s": "近く",
            "r": "ちかく",
            "p": "noun"
          },
          {
            "s": "食料品",
            "r": "しょくりょうひん",
            "p": "noun"
          },
          {
            "s": "の",
            "r": "",
            "p": "particle"
          },
          {
            "s": "消費税",
            "r": "しょうひぜい",
            "p": "noun"
          },
          {
            "s": "減税",
            "r": "げんぜい",
            "p": "noun"
          },
          {
            "s": "の",
            "r": "",
            "p": "particle"
          },
          {
            "s": "判断",
            "r": "はんだん",
            "p": "noun"
          },
          {
            "s": "を",
            "r": "",
            "p": "particle"
          },
          {
            "s": "迫る",
            "r": "せまら",
            "p": "verb"
          },
          {
            "s": "れる",
            "r": "",
            "p": "grammar"
          },
          {
            "s": "。",
            "r": "",
            "p": ""
          },
          {
            "s": "与党",
            "r": "よとう",
            "p": "noun"
          },
          {
            "s": "は",
            "r": "",
            "p": "particle"
          },
          {
            "s": "衆院選",
            "r": "しゅういんせん",
            "p": "noun"
          },
          {
            "s": "公約",
            "r": "こうやく",
            "p": "noun"
          },
          {
            "s": "で",
            "r": "",
            "p": "particle"
          },
          {
            "s": "2",
            "r": "に",
            "p": "noun"
          },
          {
            "s": "年間",
            "r": "ねんかん",
            "p": "noun"
          },
          {
            "s": "の",
            "r": "",
            "p": "particle"
          },
          {
            "s": "税率",
            "r": "ぜいりつ",
            "p": "noun"
          },
          {
            "s": "ゼロ",
            "r": "ぜろ",
            "p": "noun"
          },
          {
            "s": "を",
            "r": "",
            "p": "particle"
          },
          {
            "s": "掲げる",
            "r": "かかげ",
            "p": "verb"
          },
          {
            "s": "て",
            "r": "",
            "p": "particle"
          },
          {
            "s": "いる",
            "r": "",
            "p": "verb"
          },
          {
            "s": "た",
            "r": "",
            "p": "grammar"
          },
          {
            "s": "が",
            "r": "",
            "p": "particle"
          },
          {
            "s": "、",
            "r": "",
            "p": ""
          },
          {
            "s": "自民",
            "r": "じみん",
            "p": "noun"
          },
          {
            "s": "関係者",
            "r": "かんけいしゃ",
            "p": "noun"
          },
          {
            "s": "は",
            "r": "",
            "p": "particle"
          },
          {
            "s": "「",
            "r": "",
            "p": ""
          },
          {
            "s": "消費税",
            "r": "しょうひぜい",
            "p": "noun"
          },
          {
            "s": "を",
            "r": "",
            "p": "particle"
          },
          {
            "s": "1",
            "r": "いち",
            "p": "noun"
          },
          {
            "s": "%",
            "r": "ぱーせんと",
            "p": "noun"
          },
          {
            "s": "に",
            "r": "",
            "p": "particle"
          },
          {
            "s": "下げる",
            "r": "さげる",
            "p": "verb"
          },
          {
            "s": "中途半端",
            "r": "ちゅうとはんぱ",
            "p": "noun"
          },
          {
            "s": "だ",
            "r": "",
            "p": "grammar"
          },
          {
            "s": "対応",
            "r": "たいおう",
            "p": "noun"
          },
          {
            "s": "で",
            "r": "",
            "p": "particle"
          },
          {
            "s": "は",
            "r": "",
            "p": "particle"
          },
          {
            "s": "支持率",
            "r": "しじりつ",
            "p": "noun"
          },
          {
            "s": "が",
            "r": "",
            "p": "particle"
          },
          {
            "s": "さらに",
            "r": "",
            "p": "adverb"
          },
          {
            "s": "落ち込む",
            "r": "おちこむ",
            "p": "verb"
          },
          {
            "s": "」",
            "r": "",
            "p": ""
          },
          {
            "s": "と",
            "r": "",
            "p": "particle"
          },
          {
            "s": "懸念",
            "r": "けねん",
            "p": "noun"
          },
          {
            "s": "する",
            "r": "",
            "p": "verb"
          },
          {
            "s": "て",
            "r": "",
            "p": "particle"
          },
          {
            "s": "いる",
            "r": "",
            "p": "verb"
          },
          {
            "s": "。",
            "r": "",
            "p": ""
          }
        ],
        "audio": "assets/audio/naikaku-shijiritsu-teika-kikikan/p3.mp3"
      }
    ]
  }
]